zebracorn-0.0.1.dist-info/zip-safe
zebracorn-0.0.1.dist-info/RECORD
zebracorn-0.0.1.dist-info/METADATA
zebracorn-0.0.1.dist-info/WHEEL
zebracorn-0.0.1.dist-info/top_level.txt
zebracorn/arm64_const.py
zebracorn/m68k_const.py
zebracorn/unicorn_const.py
zebracorn/unicorn.py
zebracorn/sparc_const.py
zebracorn/x86_const.py
zebracorn/mips_const.py
zebracorn/__init__.py
zebracorn/arm_const.py
zebracorn/lib/libunicorn.so
zebracorn/include/unicorn/arm64.h
zebracorn/include/unicorn/mips.h
zebracorn/include/unicorn/unicorn.h
zebracorn/include/unicorn/sparc.h
zebracorn/include/unicorn/arm.h
zebracorn/include/unicorn/m68k.h
zebracorn/include/unicorn/x86.h
zebracorn/include/unicorn/platform.h
