Metadata-Version: 2.1
Name: zebracorn
Version: 0.0.1
Summary: A Unicorn CPU emulator fork customized for the zelos binary emulator.
Home-page: https://github.com/zeropointdynamics/zebracorn
Author: Zeropoint Dynamics
Author-email: zelos@zeropointdynamics.com
License: UNKNOWN
Platform: UNKNOWN
Classifier: Topic :: Security
Classifier: Topic :: System :: Emulators
Classifier: Development Status :: 4 - Beta
Classifier: Intended Audience :: Information Technology
Classifier: Intended Audience :: Developers
Classifier: Operating System :: MacOS :: MacOS X
Classifier: Operating System :: Microsoft :: Windows
Classifier: Operating System :: POSIX :: Linux
Classifier: Natural Language :: English
Classifier: License :: OSI Approved :: GNU Affero General Public License v3
Classifier: Programming Language :: Python
Classifier: Programming Language :: Python :: 2
Classifier: Programming Language :: Python :: 3
Classifier: Programming Language :: Python :: 3.6
Classifier: Programming Language :: Python :: 3.7
Classifier: Programming Language :: Python :: 3.8
Requires: ctypes
Provides: zebracorn
